{
   "footer_links": [
      [ "Terms", "https://dev.perl.org/licenses/artistic.html", true ],
      [ "Privacy", "https://www.openrightsgroup.org", true ],
      [ "Security", "https://github.com/pjfl/p5-app-mcat/security", true ],
      [ "Community", "https://github.com/pjfl/p5-app-mcat/wiki", true ],
      [ "Issues", "bug/list" ],
      [ "Docs", "doc/list" ],
      [ "Contact", "misc/contact" ],
      [ "Not Found", "after_an_extensive_search" ]
   ],
   "google_fonts": ["Roboto:ital,wght@0,100..900;1,100..900"],
   "local_config_file": "mcat-local.json",
   "local_fonts": [{
      "name": "DejaVu Serif", "file": "DejaVuSerif.ttf", "format": "truetype"
   }],
   "logfile": "mcat.csv",
   "navigation": {
      "logo": "img/logo.svg"
   },
   "redis": {
      "every": 1000,
      "reconnect": 20,
      "server": "localhost:6379"
   }
}
